Levenshtein/StringMatcher.py
Levenshtein/__init__.py
Levenshtein/__init__.pyi
Levenshtein/levenshtein_cpp.cp39-win32.pyd
Levenshtein/py.typed
Levenshtein-0.25.1.dist-info/COPYING
Levenshtein-0.25.1.dist-info/METADATA
Levenshtein-0.25.1.dist-info/WHEEL
Levenshtein-0.25.1.dist-info/top_level.txt
Levenshtein-0.25.1.dist-info/RECORD
