Metadata-Version: 2.1
Name: Levenshtein
Version: 0.25.1
Summary: Python extension for computing string edit distances and similarities.
Home-page: https://github.com/rapidfuzz/Levenshtein
Author: Max Bachmann
Author-email: pypi@maxbachmann.de
License: GPL
Classifier: Programming Language :: Python :: 3
Classifier: Programming Language :: Python :: 3.8
Classifier: Programming Language :: Python :: 3.9
Classifier: Programming Language :: Python :: 3.10
Classifier: Programming Language :: Python :: 3.11
Classifier: Programming Language :: Python :: 3.12
Classifier: License :: OSI Approved :: GNU General Public License v2 or later (GPLv2+)
Requires-Python: >=3.8
License-File: COPYING
Requires-Dist: rapidfuzz<4.0.0,>=3.8.0
